ru_attacker/__init__.py
ru_attacker/attacks/__init__.py
ru_attacker/attacks/add_proverb.py
ru_attacker/attacks/attack.py
ru_attacker/attacks/backtranslation.py
ru_attacker/attacks/basic_attack.py
ru_attacker/attacks/change_arguments.py
ru_attacker/attacks/paraphrase.py
ru_attacker/attacks/summarization.py
ru_attacker/attacks/utils.py
ru_attacker/attacks/word_order.py
ru_attacker/attacks/yoda_style.py
ru_attacker/attacks/constraints/__init__.py
ru_attacker/attacks/constraints/basic_constraint.py
ru_attacker/attacks/constraints/grammar_acceptability.py
ru_attacker/attacks/constraints/semantic_similarity.py
ru_attacker/attacks/constraints/transform_changed.py
ru_attacker/attacks/goal_function/__init__.py
ru_attacker/attacks/goal_function/basic_goal_function.py
ru_attacker/attacks/goal_function/label_preserving.py
ru_attacker/attacks/goal_function/negative_prediction.py
ru_attacker/attacks/search_method/__init__.py
ru_attacker/attacks/search_method/basic_search_method.py
ru_attacker/attacks/search_method/greedy_search.py
ru_attacker/attacks/transformations/__init__.py
ru_attacker/attacks/transformations/add_proverb.py
ru_attacker/attacks/transformations/backtranslation.py
ru_attacker/attacks/transformations/basic_transformation.py
ru_attacker/attacks/transformations/change_arguments.py
ru_attacker/attacks/transformations/paraphrase.py
ru_attacker/attacks/transformations/summarization.py
ru_attacker/attacks/transformations/word_order.py
ru_attacker/attacks/transformations/yoda_style.py
ru_attacker/models/Roberta_model.py
ru_attacker/models/T5_model.py
ru_attacker/models/__init__.py
ru_attacker/models/basic_model.py
ru_attacker/models/set_dataset.py
ru_attacker-0.0.5.dist-info/LICENSE
ru_attacker-0.0.5.dist-info/METADATA
ru_attacker-0.0.5.dist-info/WHEEL
ru_attacker-0.0.5.dist-info/top_level.txt
ru_attacker-0.0.5.dist-info/RECORD
