Metadata-Version: 2.1
Name: ru-attacker
Version: 0.0.5
Summary: A python package for attacking Russian NLP models
Home-page: https://github.com/yuliya1324/ru_attacker
Author: Julia Korotkova
Author-email: koylenka15@gmail.com
License: UNKNOWN
Platform: UNKNOWN
Classifier: Programming Language :: Python :: 3.8
Classifier: License :: OSI Approved :: MIT License
Classifier: Operating System :: OS Independent
Requires-Python: >=3.6
License-File: LICENSE
Requires-Dist: tqdm
Requires-Dist: torch
Requires-Dist: pandas
Requires-Dist: numpy
Requires-Dist: pymorphy2
Requires-Dist: nltk
Requires-Dist: transformers
Requires-Dist: jsonlines
Requires-Dist: sentencepiece
Requires-Dist: tensorflow-text (>=2.0.0rc0)
Requires-Dist: natasha
Requires-Dist: language-tool-python
